{"extracted_claim": "The user is claiming damage to the left side mirror.", "evidence_standard_met": true, "evidence_standard_met_reason": "The image clearly shows the left side mirror is broken and detached from the vehicle.", "issue_type": "broken_part", "object_part": "side_mirror", "claim_status": "supported", "claim_status_justification": "Image 1 clearly shows the left side mirror is broken and hanging from the vehicle, supporting the user's claim.", "supporting_image_ids": ["img_1"], "severity": "high", "risk_flags": ["user_history_risk"]}